wheelbot_dataset/__init__.py
wheelbot_dataset/__main__.py
wheelbot_dataset/consolidate.py
wheelbot_dataset/download.py
wheelbot_dataset/fix_yaw_data.py
wheelbot_dataset/record.py
wheelbot_dataset/recording/__init__.py
wheelbot_dataset/recording/csvplot.py
wheelbot_dataset/recording/experiment.py
wheelbot_dataset/recording/geometry_sequences.py
wheelbot_dataset/recording/prb_sequences.py
wheelbot_dataset/recording/utils.py
wheelbot_dataset/usage/__init__.py
wheelbot_dataset/usage/dataset.py
wheelbot_dataset/usage/visualization.py
wheelbot_dataset-0.1.2.dist-info/licenses/LICENSE
wheelbot_dataset-0.1.2.dist-info/METADATA
wheelbot_dataset-0.1.2.dist-info/WHEEL
wheelbot_dataset-0.1.2.dist-info/entry_points.txt
wheelbot_dataset-0.1.2.dist-info/top_level.txt
wheelbot_dataset-0.1.2.dist-info/RECORD
