Metadata-Version: 2.4
Name: wheelbot-dataset
Version: 0.1.2
Summary: The Mini Wheelbot Dataset: High-Fidelity Data for Robot Learning
Author-email: Henrik Hose <henrik.hose@rwth-aachen.de>, Paul Brunzema <brunzema@dsme.rwth-aachen.de>
Maintainer-email: Henrik Hose <henrik.hose@rwth-aachen.de>
License-Expression: MIT
Project-URL: Homepage, https://github.com/wheelbot/dataset
Project-URL: Repository, https://github.com/wheelbot/dataset
Keywords: robotics,dataset,wheelbot,self-balancing,machine-learning,dynamics,control,motion-capture,imu
Classifier: Development Status :: 4 - Beta
Classifier: Intended Audience :: Science/Research
Classifier: Intended Audience :: Developers
Classifier: Programming Language :: Python :: 3
Classifier: Programming Language :: Python :: 3.11
Classifier: Programming Language :: Python :: 3.12
Classifier: Programming Language :: Python :: 3.13
Classifier: Programming Language :: Python :: 3.14
Classifier: Topic :: Scientific/Engineering :: Artificial Intelligence
Classifier: Topic :: Scientific/Engineering :: Information Analysis
Classifier: Operating System :: OS Independent
Requires-Python: >=3.11
License-File: LICENSE
Requires-Dist: numpy
Requires-Dist: pandas
Requires-Dist: matplotlib
Requires-Dist: paramiko
Requires-Dist: fire
Requires-Dist: requests
Provides-Extra: dev
Requires-Dist: pytest; extra == "dev"
Requires-Dist: scipy; extra == "dev"
Provides-Extra: all
Requires-Dist: scipy; extra == "all"
Requires-Dist: jax; extra == "all"
Requires-Dist: jaxlib; extra == "all"
Requires-Dist: equinox; extra == "all"
Requires-Dist: optax; extra == "all"
Dynamic: license-file
